README.md
setup.py
kb_stopwatch.egg-info/PKG-INFO
kb_stopwatch.egg-info/SOURCES.txt
kb_stopwatch.egg-info/dependency_links.txt
kb_stopwatch.egg-info/entry_points.txt
kb_stopwatch.egg-info/requires.txt
kb_stopwatch.egg-info/top_level.txt
kbstopwatch/__init__.py
kbstopwatch/main.py
kbstopwatch/version.py