Metadata-Version: 2.1
Name: kb-stopwatch
Version: 0.0.2
Summary: Keyboard controlled stopwatch with no window focus required
Home-page: https://github.com/mwiens91/kb-stopwatch
Author: Matt Wiens
Author-email: mwiens91@gmail.com
License: MIT
Platform: UNKNOWN
Classifier: Intended Audience :: End Users/Desktop
Classifier: License :: OSI Approved :: MIT License
Classifier: Programming Language :: Python
Classifier: Programming Language :: Python :: 3
Classifier: Programming Language :: Python :: 3.5
Classifier: Programming Language :: Python :: 3.6
Classifier: Programming Language :: Python :: 3.7
Classifier: Programming Language :: Python :: 3 :: Only
Requires-Python: >=3.5
